flask_manage_webpack/__init__.py
flask_manage_webpack/cli.py
flask_manage_webpack/manage_webpack.py
flask_manage_webpack/utils.py
flask_manage_webpack/__pycache__/__init__.cpython-37.pyc
flask_manage_webpack/__pycache__/cli.cpython-37.pyc
flask_manage_webpack/__pycache__/manage_webpack.cpython-37.pyc
flask_manage_webpack/__pycache__/utils.cpython-37.pyc
flask_manage_webpack/template/package.json
flask_manage_webpack/template/postcss.config.js
flask_manage_webpack/template/webpack.config.js
flask_manage_webpack/template/assets/css/main.css
flask_manage_webpack/template/assets/js/main.js
flask_manage_webpack/template/assets/js/module/empty.js
flask_manage_webpack/template/assets/js/view/home.js
Flask_Manage_Webpack-1.4.1.dist-info/LICENSE
Flask_Manage_Webpack-1.4.1.dist-info/METADATA
Flask_Manage_Webpack-1.4.1.dist-info/WHEEL
Flask_Manage_Webpack-1.4.1.dist-info/entry_points.txt
Flask_Manage_Webpack-1.4.1.dist-info/top_level.txt
Flask_Manage_Webpack-1.4.1.dist-info/RECORD
