Metadata-Version: 2.1
Name: Flask-Manage-Webpack
Version: 1.4.1
Summary: Flask extension for connecting and managing webpack assets
Home-page: https://github.com/psdon/Flask-Manage-Webpack
Author: Paulo Sairel Don
Author-email: connect.psdon@gmail.com
License: MIT
Keywords: flask,webpack,manifest
Platform: any
Classifier: Intended Audience :: Developers
Classifier: Topic :: Internet :: WWW/HTTP :: Dynamic Content
Classifier: Topic :: Software Development :: Libraries :: Python Modules
Classifier: License :: OSI Approved :: MIT License
Classifier: Programming Language :: Python :: 3
Requires-Python: >=3.6
Requires-Dist: requests
Requires-Dist: Flask (>=1.0)
